[
  {
    "model": "courses.payment",
    "fields": {
      "student": 8,
      "payment_date": "2023-07-18",
      "course": 1,
      "amount": 99,
      "payment_type": "bank"
    }
  },
  {
    "model": "courses.payment",
    "fields": {
      "student": 7,
      "payment_date": "2023-07-25",
      "course": 1,
      "amount": 99,
      "payment_type": "cash"
    }
  },
  {
    "model": "courses.payment",
    "fields": {
      "student": 6,
      "payment_date": "2023-09-25",
      "lesson": 1,
      "amount": 19,
      "payment_type": "bank"
    }
  },
  {
    "model": "courses.payment",
    "fields": {
      "student": 6,
      "payment_date": "2023-10-25",
      "lesson": 2,
      "amount": 39,
      "payment_type": "bank"
    }
  },
  {
    "model": "courses.payment",
    "fields": {
      "student": 6,
      "payment_date": "2023-11-25",
      "lesson": 3,
      "amount": 29,
      "payment_type": "bank"
    }
  },
  {
    "model": "courses.payment",
    "fields": {
      "student": 5,
      "payment_date": "2023-07-18",
      "lesson": 3,
      "amount": 29,
      "payment_type": "cash"
    }
  },
  {
    "model": "courses.payment",
    "fields": {
      "student": 4,
      "payment_date": "2023-11-30",
      "lesson": 3,
      "amount": 29,
      "payment_type": "bank"
    }
  },
  {
    "model": "courses.payment",
    "fields": {
      "student": 3,
      "payment_date": "2023-07-18",
      "course": 2,
      "amount": 299,
      "payment_type": "cash"
    }
  },
  {
    "model": "courses.payment",
    "fields": {
      "student": 2,
      "payment_date": "2023-10-25",
      "lesson": 1,
      "amount": 19,
      "payment_type": "cash"
    }
  },
  {
    "model": "courses.payment",
    "fields": {
      "student": 2,
      "payment_date": "2023-10-25",
      "course": 2,
      "amount": 129,
      "payment_type": "cash"
    }
  }
]
